espwrap/__init__.py
espwrap/base.py
espwrap/adaptors/__init__.py
espwrap/adaptors/mandrill.py
espwrap/adaptors/noop.py
espwrap/adaptors/sendgrid.py
espwrap/adaptors/sendgrid_common.py
espwrap/adaptors/sendgrid_v3.py
espwrap-2.0.19.dist-info/LICENSE
espwrap-2.0.19.dist-info/METADATA
espwrap-2.0.19.dist-info/WHEEL
espwrap-2.0.19.dist-info/top_level.txt
espwrap-2.0.19.dist-info/RECORD
