Metadata-Version: 2.1
Name: espwrap
Version: 2.0.19
Summary: A light wrapper around email service providers
Home-page: https://github.com/SpotOnInc/espwrap
Download-URL: https://github.com/SpotOnInc/espwrap/2.0.19
Author: SpotOn
Author-email: josh@spoton.com
License: MIT
Platform: any
License-File: LICENSE
Provides-Extra: mandrill
Requires-Dist: mandrill (>=1.0.57) ; extra == 'mandrill'
Provides-Extra: sendgrid
Requires-Dist: smtpapi (>=0.3.1) ; extra == 'sendgrid'
Requires-Dist: sendgrid (==6.9.7) ; extra == 'sendgrid'
